wtprogress/__init__.py
wtprogress-0.0.1.dist-info/LICENSE
wtprogress-0.0.1.dist-info/METADATA
wtprogress-0.0.1.dist-info/WHEEL
wtprogress-0.0.1.dist-info/top_level.txt
wtprogress-0.0.1.dist-info/RECORD
