Metadata-Version: 2.1
Name: wtprogress
Version: 0.0.1
Summary: show progress on windows terminal taskbar icon
Home-page: https://github.com/oxygen-dioxide/wtprogress
Author: oxygen dioxide
Author-email: 1463567152@qq.com
License: MIT
Platform: UNKNOWN
Classifier: License :: OSI Approved :: MIT License
Classifier: Programming Language :: Python
Classifier: Programming Language :: Python :: 3
Classifier: Programming Language :: Python :: 3.9
Classifier: Programming Language :: Python :: 3.8
Classifier: Programming Language :: Python :: 3.7
Classifier: Programming Language :: Python :: 3.6
Classifier: Programming Language :: Python :: 3.5
Classifier: Topic :: Terminals :: Terminal Emulators/X Terminals
Classifier: Programming Language :: Python :: Implementation :: CPython
Requires-Python: >=3.5.0
